{
  "cinemaId": "Z2lkOi8vY2luZW1hLzg=",
  "slug": "the-super-elfkins-uk",
  "response": {
    "movieBySlug": {
      "offlineRental": {
        "end": "2025-04-09T00:00:00.000Z",
        "start": "2025-03-27T00:00:00.000Z",
        "status": "ACTIVE",
        "labels": [
          {
            "id": "Z2lkOi8vb2ZmbGluZWxhYmVsLzEwMw==",
            "name": "Доступне кіно",
            "group": null,
            "sortPriority": 70
          },
          {
            "id": "Z2lkOi8vb2ZmbGluZWxhYmVsLzEyMQ==",
            "name": "Діють знижки",
            "group": "DISCOUNT",
            "sortPriority": 59
          }
        ],
        "calendar": [
          "2025-03-28T00:00:00.000Z",
          "2025-03-29T00:00:00.000Z",
          "2025-03-30T00:00:00.000Z",
          "2025-03-31T00:00:00.000Z",
          "2025-04-01T00:00:00.000Z",
          "2025-04-02T00:00:00.000Z"
        ],
        "rentalTechnologies": [
          {
            "id": "Z2lkOi8vcmVudGFsdGVjaG5vbG9neS81",
            "name": "Cinetech+",
            "slug": "сinetech"
          }
        ],
        "sessionsNumber": 6,
        "sessions": [
          {
            "canPayWithBonuses": false,
            "dimensionType": "2D",
            "durationInSec": 4560,
            "startSessionAt": "2025-03-28T11:30:00.000Z",
            "endSessionAt": "2025-03-28T12:46:00.000Z",
            "countFreeSeats": 127,
            "labels": [],
            "cinemaHall": {
              "id": "Z2lkOi8vY2luZW1haGFsbC8xMDY=",
              "activeStatus": "ACTIVE",
              "doorNumberEntranceToHall": 3,
              "isAlphabeticalRowsEnumeration": false,
              "rows": [
                {
                  "rowNumber": "1",
                  "seats": [
                    {
                      "id": "Z2lkOi8vc2VhdC8xNDMwMQ==",
                      "type": "STANDARD",
                      "rowNumber": "1",
                      "seatNumber": 1,
                      "state": "ACTIVE"
                    },
                    {
                      "id": "Z2lkOi8vc2VhdC8xNDMwMA==",
                      "type": "STANDARD",
                      "rowNumber": "1",
                      "seatNumber": 2,
                      "state": "ACTIVE"
                    },
                    {
                      "id": "Z2lkOi8vc2VhdC8xNDI5OQ==",
                      "type": "STANDARD",
                      "rowNumber": "1",
                      "seatNumber": 3,
                      "state": "ACTIVE"
                    },
                    {
                      "id": "Z2lkOi8vc2VhdC8xNDI5OA==",
                      "type": "STANDARD",
                      "rowNumber": "1",
                      "seatNumber": 4,
                      "state": "ACTIVE"
                    },
                    {
                      "id": "Z2lkOi8vc2VhdC8xNDI5Nw==",
                      "type": "STANDARD",
                      "rowNumber": "1",
                      "seatNumber": 5,
                      "state": "ACTIVE"
                    },
                    {
                      "id": "Z2lkOi8vc2VhdC8xNDI5Ng==",
                      "type": "STANDARD",
                      "rowNumber": "1",
                      "seatNumber": 6,
                      "state": "ACTIVE"
                    }
                  ]
                },
                {
                  "rowNumber": "2",
                  "seats": [
                    {
                      "id": "Z2lkOi8vc2VhdC8xNDMxMw==",
                      "type": "STANDARD",
                      "rowNumber": "2",
                      "seatNumber": 1,
                      "state": "ACTIVE"
                    },
                    {
                      "id": "Z2lkOi8vc2VhdC8xNDMxMg==",
                      "type": "STANDARD",
                      "rowNumber": "2",
                      "seatNumber": 2,
                      "state": "ACTIVE"
                    },
                    {
                      "id": "Z2lkOi8vc2VhdC8xNDMxMQ==",
                      "type": "STANDARD",
                      "rowNumber": "2",
                      "seatNumber": 3,
                      "state": "ACTIVE"
                    },
                    {
                      "id": "Z2lkOi8vc2VhdC8xNDMxMA==",
                      "type": "STANDARD",
                      "rowNumber": "2",
                      "seatNumber": 4,
                      "state": "ACTIVE"
                    },
                    {
                      "id": "Z2lkOi8vc2VhdC8xNDMwOQ==",
                      "type": "STANDARD",
                      "rowNumber": "2",
                      "seatNumber": 5,
                      "state": "ACTIVE"
                    },
                    {
                      "id": "Z2lkOi8vc2VhdC8xNDMwOA==",
                      "type": "STANDARD",
                      "rowNumber": "2",
                      "seatNumber": 6,
                      "state": "ACTIVE"
                    },
                    {
                      "id": "Z2lkOi8vc2VhdC8xNDMwNw==",
                      "type": "STANDARD",
                      "rowNumber": "2",
                      "seatNumber": 7,
                      "state": "ACTIVE"
                    },
                    {
                      "id": "Z2lkOi8vc2VhdC8xNDMwNg==",
                      "type": "STANDARD",
                      "rowNumber": "2",
                      "seatNumber": 8,
                      "state": "ACTIVE"
                    },
                    {
                      "id": "Z2lkOi8vc2VhdC8xNDMwNQ==",
                      "type": "STANDARD",
                      "rowNumber": "2",
                      "seatNumber": 9,
                      "state": "ACTIVE"
                    },
                    {
                      "id": "Z2lkOi8vc2VhdC8xNDMwNA==",
                      "type": "STANDARD",
                      "rowNumber": "2",
                      "seatNumber": 10,
                      "state": "ACTIVE"
                    },
                    {
                      "id": "Z2lkOi8vc2VhdC8xNDMwMw==",
                      "type": "STANDARD",
                      "rowNumber": "2",
                      "seatNumber": 11,
                      "state": "ACTIVE"
                    },
                    {
                      "id": "Z2lkOi8vc2VhdC8xNDMwMg==",
                      "type": "STANDARD",
                      "rowNumber": "2",
                      "seatNumber": 12,
                      "state": "ACTIVE"
                    }
                  ]
                },
                {
                  "rowNumber": "3",
                  "seats": [
                    {
                      "id": "Z2lkOi8vc2VhdC8xNDMyNQ==",
                      "type": "STANDARD",
                      "rowNumber": "3",
                      "seatNumber": 1,
                      "state": "ACTIVE"
                    },
                    {
                      "id": "Z2lkOi8vc2VhdC8xNDMyNA==",
                      "type": "STANDARD",
                      "rowNumber": "3",
                      "seatNumber": 2,
                      "state": "ACTIVE"
                    },
                    {
                      "id": "Z2lkOi8vc2VhdC8xNDMyMw==",
                      "type": "STANDARD",
                      "rowNumber": "3",
                      "seatNumber": 3,
                      "state": "ACTIVE"
                    },
                    {
                      "id": "Z2lkOi8vc2VhdC8xNDMyMg==",
                      "type": "STANDARD",
                      "rowNumber": "3",
                      "seatNumber": 4,
                      "state": "ACTIVE"
                    },
                    {
                      "id": "Z2lkOi8vc2VhdC8xNDMyMQ==",
                      "type": "STANDARD",
                      "rowNumber": "3",
                      "seatNumber": 5,
                      "state": "ACTIVE"
                    },
                    {
                      "id": "Z2lkOi8vc2VhdC8xNDMyMA==",
                      "type": "STANDARD",
                      "rowNumber": "3",
                      "seatNumber": 6,
                      "state": "ACTIVE"
                    },
                    {
                      "id": "Z2lkOi8vc2VhdC8xNDMxOQ==",
                      "type": "STANDARD",
                      "rowNumber": "3",
                      "seatNumber": 7,
                      "state": "ACTIVE"
                    },
                    {
                      "id": "Z2lkOi8vc2VhdC8xNDMxOA==",
                      "type": "STANDARD",
                      "rowNumber": "3",
                      "seatNumber": 8,
                      "state": "ACTIVE"
                    },
                    {
                      "id": "Z2lkOi8vc2VhdC8xNDMxNw==",
                      "type": "STANDARD",
                      "rowNumber": "3",
                      "seatNumber": 9,
                      "state": "ACTIVE"
                    },
                    {
                      "id": "Z2lkOi8vc2VhdC8xNDMxNg==",
                      "type": "STANDARD",
                      "rowNumber": "3",
                      "seatNumber": 10,
                      "state": "ACTIVE"
                    },
                    {
                      "id": "Z2lkOi8vc2VhdC8xNDMxNQ==",
                      "type": "STANDARD",
                      "rowNumber": "3",
                      "seatNumber": 11,
                      "state": "ACTIVE"
                    },
                    {
                      "id": "Z2lkOi8vc2VhdC8xNDMxNA==",
                      "type": "STANDARD",
                      "rowNumber": "3",
                      "seatNumber": 12,
                      "state": "ACTIVE"
                    }
                  ]
                },
                {
                  "rowNumber": "4",
                  "seats": [
                    {
                      "id": "Z2lkOi8vc2VhdC8xNDMzNw==",
                      "type": "STANDARD",
                      "rowNumber": "4",
                      "seatNumber": 1,
                      "state": "ACTIVE"
                    },
                    {
                      "id": "Z2lkOi8vc2VhdC8xNDMzNg==",
                      "type": "STANDARD",
                      "rowNumber": "4",
                      "seatNumber": 2,
                      "state": "ACTIVE"
                    },
                    {
                      "id": "Z2lkOi8vc2VhdC8xNDMzNQ==",
                      "type": "STANDARD",
                      "rowNumber": "4",
                      "seatNumber": 3,
                      "state": "ACTIVE"
                    },
                    {
                      "id": "Z2lkOi8vc2VhdC8xNDMzNA==",
                      "type": "STANDARD",
                      "rowNumber": "4",
                      "seatNumber": 4,
                      "state": "ACTIVE"
                    },
                    {
                      "id": "Z2lkOi8vc2VhdC8xNDMzMw==",
                      "type": "STANDARD",
                      "rowNumber": "4",
                      "seatNumber": 5,
                      "state": "ACTIVE"
                    },
                    {
                      "id": "Z2lkOi8vc2VhdC8xNDMzMg==",
                      "type": "STANDARD",
                      "rowNumber": "4",
                      "seatNumber": 6,
                      "state": "ACTIVE"
                    },
                    {
                      "id": "Z2lkOi8vc2VhdC8xNDMzMQ==",
                      "type": "STANDARD",
                      "rowNumber": "4",
                      "seatNumber": 7,
                      "state": "ACTIVE"
                    },
                    {
                      "id": "Z2lkOi8vc2VhdC8xNDMzMA==",
                      "type": "STANDARD",
                      "rowNumber": "4",
                      "seatNumber": 8,
                      "state": "ACTIVE"
                    },
                    {
                      "id": "Z2lkOi8vc2VhdC8xNDMyOQ==",
                      "type": "STANDARD",
                      "rowNumber": "4",
                      "seatNumber": 9,
                      "state": "ACTIVE"
                    },
                    {
                      "id": "Z2lkOi8vc2VhdC8xNDMyOA==",
                      "type": "STANDARD",
                      "rowNumber": "4",
                      "seatNumber": 10,
                      "state": "ACTIVE"
                    },
                    {
                      "id": "Z2lkOi8vc2VhdC8xNDMyNw==",
                      "type": "STANDARD",
                      "rowNumber": "4",
                      "seatNumber": 11,
                      "state": "ACTIVE"
                    },
                    {
                      "id": "Z2lkOi8vc2VhdC8xNDMyNg==",
                      "type": "STANDARD",
                      "rowNumber": "4",
                      "seatNumber": 12,
                      "state": "ACTIVE"
                    }
                  ]
                },
                {
                  "rowNumber": "5",
                  "seats": [
                    {
                      "id": "Z2lkOi8vc2VhdC8xNDM0OQ==",
                      "type": "STANDARD",
                      "rowNumber": "5",
                      "seatNumber": 1,
                      "state": "ACTIVE"
                    },
                    {
                      "id": "Z2lkOi8vc2VhdC8xNDM0OA==",
                      "type": "STANDARD",
                      "rowNumber": "5",
                      "seatNumber": 2,
                      "state": "ACTIVE"
                    },
                    {
                      "id": "Z2lkOi8vc2VhdC8xNDM0Nw==",
                      "type": "STANDARD",
                      "rowNumber": "5",
                      "seatNumber": 3,
                      "state": "ACTIVE"
                    },
                    {
                      "id": "Z2lkOi8vc2VhdC8xNDM0Ng==",
                      "type": "STANDARD",
                      "rowNumber": "5",
                      "seatNumber": 4,
                      "state": "ACTIVE"
                    },
                    {
                      "id": "Z2lkOi8vc2VhdC8xNDM0NQ==",
                      "type": "STANDARD",
                      "rowNumber": "5",
                      "seatNumber": 5,
                      "state": "ACTIVE"
                    },
                    {
                      "id": "Z2lkOi8vc2VhdC8xNDM0NA==",
                      "type": "STANDARD",
                      "rowNumber": "5",
                      "seatNumber": 6,
                      "state": "ACTIVE"
                    },
                    {
                      "id": "Z2lkOi8vc2VhdC8xNDM0Mw==",
                      "type": "STANDARD",
                      "rowNumber": "5",
                      "seatNumber": 7,
                      "state": "ACTIVE"
                    },
                    {
                      "id": "Z2lkOi8vc2VhdC8xNDM0Mg==",
                      "type": "STANDARD",
                      "rowNumber": "5",
                      "seatNumber": 8,
                      "state": "ACTIVE"
                    },
                    {
                      "id": "Z2lkOi8vc2VhdC8xNDM0MQ==",
                      "type": "STANDARD",
                      "rowNumber": "5",
                      "seatNumber": 9,
                      "state": "ACTIVE"
                    },
                    {
                      "id": "Z2lkOi8vc2VhdC8xNDM0MA==",
                      "type": "STANDARD",
                      "rowNumber": "5",
                      "seatNumber": 10,
                      "state": "ACTIVE"
                    },
                    {
                      "id": "Z2lkOi8vc2VhdC8xNDMzOQ==",
                      "type": "STANDARD",
                      "rowNumber": "5",
                      "seatNumber": 11,
                      "state": "ACTIVE"
                    },
                    {
                      "id": "Z2lkOi8vc2VhdC8xNDMzOA==",
                      "type": "STANDARD",
                      "rowNumber": "5",
                      "seatNumber": 12,
                      "state": "ACTIVE"
                    }
                  ]
                },
                {
                  "rowNumber": "6",
                  "seats": [
                    {
                      "id": "Z2lkOi8vc2VhdC8xNDM2MQ==",
                      "type": "STANDARD",
                      "rowNumber": "6",
                      "seatNumber": 1,
                      "state": "ACTIVE"
                    },
                    {
                      "id": "Z2lkOi8vc2VhdC8xNDM2MA==",
                      "type": "STANDARD",
                      "rowNumber": "6",
                      "seatNumber": 2,
                      "state": "ACTIVE"
                    },
                    {
                      "id": "Z2lkOi8vc2VhdC8xNDM1OQ==",
                      "type": "STANDARD",
                      "rowNumber": "6",
                      "seatNumber": 3,
                      "state": "ACTIVE"
                    },
                    {
                      "id": "Z2lkOi8vc2VhdC8xNDM1OA==",
                      "type": "STANDARD",
                      "rowNumber": "6",
                      "seatNumber": 4,
                      "state": "ACTIVE"
                    },
                    {
                      "id": "Z2lkOi8vc2VhdC8xNDM1Nw==",
                      "type": "STANDARD",
                      "rowNumber": "6",
                      "seatNumber": 5,
                      "state": "ACTIVE"
                    },
                    {
                      "id": "Z2lkOi8vc2VhdC8xNDM1Ng==",
                      "type": "STANDARD",
                      "rowNumber": "6",
                      "seatNumber": 6,
                      "state": "ACTIVE"
                    },
                    {
                      "id": "Z2lkOi8vc2VhdC8xNDM1NQ==",
                      "type": "STANDARD",
                      "rowNumber": "6",
                      "seatNumber": 7,
                      "state": "ACTIVE"
                    },
                    {
                      "id": "Z2lkOi8vc2VhdC8xNDM1NA==",
                      "type": "STANDARD",
                      "rowNumber": "6",
                      "seatNumber": 8,
                      "state": "ACTIVE"
                    },
                    {
                      "id": "Z2lkOi8vc2VhdC8xNDM1Mw==",
                      "type": "STANDARD",
                      "rowNumber": "6",
                      "seatNumber": 9,
                      "state": "ACTIVE"
                    },
                    {
                      "id": "Z2lkOi8vc2VhdC8xNDM1Mg==",
                      "type": "STANDARD",
                      "rowNumber": "6",
                      "seatNumber": 10,
                      "state": "ACTIVE"
                    },
                    {
                      "id": "Z2lkOi8vc2VhdC8xNDM1MQ==",
                      "type": "STANDARD",
                      "rowNumber": "6",
                      "seatNumber": 11,
                      "state": "ACTIVE"
                    },
                    {
                      "id": "Z2lkOi8vc2VhdC8xNDM1MA==",
                      "type": "STANDARD",
                      "rowNumber": "6",
                      "seatNumber": 12,
                      "state": "ACTIVE"
                    }
                  ]
                },
                {
                  "rowNumber": "7",
                  "seats": [
                    {
                      "id": "Z2lkOi8vc2VhdC8xNDM3Mw==",
                      "type": "STANDARD",
                      "rowNumber": "7",
                      "seatNumber": 1,
                      "state": "ACTIVE"
                    },
                    {
                      "id": "Z2lkOi8vc2VhdC8xNDM3Mg==",
                      "type": "STANDARD",
                      "rowNumber": "7",
                      "seatNumber": 2,
                      "state": "ACTIVE"
                    },
                    {
                      "id": "Z2lkOi8vc2VhdC8xNDM3MQ==",
                      "type": "STANDARD",
                      "rowNumber": "7",
                      "seatNumber": 3,
                      "state": "ACTIVE"
                    },
                    {
                      "id": "Z2lkOi8vc2VhdC8xNDM3MA==",
                      "type": "STANDARD",
                      "rowNumber": "7",
                      "seatNumber": 4,
                      "state": "ACTIVE"
                    },
                    {
                      "id": "Z2lkOi8vc2VhdC8xNDM2OQ==",
                      "type": "STANDARD",
                      "rowNumber": "7",
                      "seatNumber": 5,
                      "state": "ACTIVE"
                    },
                    {
                      "id": "Z2lkOi8vc2VhdC8xNDM2OA==",
                      "type": "STANDARD",
                      "rowNumber": "7",
                      "seatNumber": 6,
                      "state": "ACTIVE"
                    },
                    {
                      "id": "Z2lkOi8vc2VhdC8xNDM2Nw==",
                      "type": "STANDARD",
                      "rowNumber": "7",
                      "seatNumber": 7,
                      "state": "ACTIVE"
                    },
                    {
                      "id": "Z2lkOi8vc2VhdC8xNDM2Ng==",
                      "type": "STANDARD",
                      "rowNumber": "7",
                      "seatNumber": 8,
                      "state": "ACTIVE"
                    },
                    {
                      "id": "Z2lkOi8vc2VhdC8xNDM2NQ==",
                      "type": "STANDARD",
                      "rowNumber": "7",
                      "seatNumber": 9,
                      "state": "ACTIVE"
                    },
                    {
                      "id": "Z2lkOi8vc2VhdC8xNDM2NA==",
                      "type": "STANDARD",
                      "rowNumber": "7",
                      "seatNumber": 10,
                      "state": "ACTIVE"
                    },
                    {
                      "id": "Z2lkOi8vc2VhdC8xNDM2Mw==",
                      "type": "STANDARD",
                      "rowNumber": "7",
                      "seatNumber": 11,
                      "state": "ACTIVE"
                    },
                    {
                      "id": "Z2lkOi8vc2VhdC8xNDM2Mg==",
                      "type": "STANDARD",
                      "rowNumber": "7",
                      "seatNumber": 12,
                      "state": "ACTIVE"
                    }
                  ]
                },
                {
                  "rowNumber": "8",
                  "seats": [
                    {
                      "id": "Z2lkOi8vc2VhdC8xNDM4Nw==",
                      "type": "STANDARD",
                      "rowNumber": "8",
                      "seatNumber": 1,
                      "state": "ACTIVE"
                    },
                    {
                      "id": "Z2lkOi8vc2VhdC8xNDM4Ng==",
                      "type": "STANDARD",
                      "rowNumber": "8",
                      "seatNumber": 2,
                      "state": "ACTIVE"
                    },
                    {
                      "id": "Z2lkOi8vc2VhdC8xNDM4NQ==",
                      "type": "STANDARD",
                      "rowNumber": "8",
                      "seatNumber": 3,
                      "state": "ACTIVE"
                    },
                    {
                      "id": "Z2lkOi8vc2VhdC8xNDM4NA==",
                      "type": "STANDARD",
                      "rowNumber": "8",
                      "seatNumber": 4,
                      "state": "ACTIVE"
                    },
                    {
                      "id": "Z2lkOi8vc2VhdC8xNDM4Mw==",
                      "type": "STANDARD",
                      "rowNumber": "8",
                      "seatNumber": 5,
                      "state": "ACTIVE"
                    },
                    {
                      "id": "Z2lkOi8vc2VhdC8xNDM4Mg==",
                      "type": "STANDARD",
                      "rowNumber": "8",
                      "seatNumber": 6,
                      "state": "ACTIVE"
                    },
                    {
                      "id": "Z2lkOi8vc2VhdC8xNDM4MQ==",
                      "type": "STANDARD",
                      "rowNumber": "8",
                      "seatNumber": 7,
                      "state": "ACTIVE"
                    },
                    {
                      "id": "Z2lkOi8vc2VhdC8xNDM4MA==",
                      "type": "STANDARD",
                      "rowNumber": "8",
                      "seatNumber": 8,
                      "state": "SOLD"
                    },
                    {
                      "id": "Z2lkOi8vc2VhdC8xNDM3OQ==",
                      "type": "STANDARD",
                      "rowNumber": "8",
                      "seatNumber": 9,
                      "state": "SOLD"
                    },
                    {
                      "id": "Z2lkOi8vc2VhdC8xNDM3OA==",
                      "type": "STANDARD",
                      "rowNumber": "8",
                      "seatNumber": 10,
                      "state": "ACTIVE"
                    },
                    {
                      "id": "Z2lkOi8vc2VhdC8xNDM3Nw==",
                      "type": "STANDARD",
                      "rowNumber": "8",
                      "seatNumber": 11,
                      "state": "ACTIVE"
                    },
                    {
                      "id": "Z2lkOi8vc2VhdC8xNDM3Ng==",
                      "type": "STANDARD",
                      "rowNumber": "8",
                      "seatNumber": 12,
                      "state": "ACTIVE"
                    },
                    {
                      "id": "Z2lkOi8vc2VhdC8xNDM3NQ==",
                      "type": "STANDARD",
                      "rowNumber": "8",
                      "seatNumber": 13,
                      "state": "ACTIVE"
                    },
                    {
                      "id": "Z2lkOi8vc2VhdC8xNDM3NA==",
                      "type": "STANDARD",
                      "rowNumber": "8",
                      "seatNumber": 14,
                      "state": "ACTIVE"
                    }
                  ]
                },
                {
                  "rowNumber": "9",
                  "seats": [
                    {
                      "id": "Z2lkOi8vc2VhdC8xNDQwMQ==",
                      "type": "STANDARD",
                      "rowNumber": "9",
                      "seatNumber": 1,
                      "state": "ACTIVE"
                    },
                    {
                      "id": "Z2lkOi8vc2VhdC8xNDQwMA==",
                      "type": "STANDARD",
                      "rowNumber": "9",
                      "seatNumber": 2,
                      "state": "ACTIVE"
                    },
                    {
                      "id": "Z2lkOi8vc2VhdC8xNDM5OQ==",
                      "type": "STANDARD",
                      "rowNumber": "9",
                      "seatNumber": 3,
                      "state": "ACTIVE"
                    },
                    {
                      "id": "Z2lkOi8vc2VhdC8xNDM5OA==",
                      "type": "STANDARD",
                      "rowNumber": "9",
                      "seatNumber": 4,
                      "state": "ACTIVE"
                    },
                    {
                      "id": "Z2lkOi8vc2VhdC8xNDM5Nw==",
                      "type": "STANDARD",
                      "rowNumber": "9",
                      "seatNumber": 5,
                      "state": "ACTIVE"
                    },
                    {
                      "id": "Z2lkOi8vc2VhdC8xNDM5Ng==",
                      "type": "STANDARD",
                      "rowNumber": "9",
                      "seatNumber": 6,
                      "state": "ACTIVE"
                    },
                    {
                      "id": "Z2lkOi8vc2VhdC8xNDM5NQ==",
                      "type": "STANDARD",
                      "rowNumber": "9",
                      "seatNumber": 7,
                      "state": "ACTIVE"
                    },
                    {
                      "id": "Z2lkOi8vc2VhdC8xNDM5NA==",
                      "type": "STANDARD",
                      "rowNumber": "9",
                      "seatNumber": 8,
                      "state": "ACTIVE"
                    },
                    {
                      "id": "Z2lkOi8vc2VhdC8xNDM5Mw==",
                      "type": "STANDARD",
                      "rowNumber": "9",
                      "seatNumber": 9,
                      "state": "ACTIVE"
                    },
                    {
                      "id": "Z2lkOi8vc2VhdC8xNDM5Mg==",
                      "type": "STANDARD",
                      "rowNumber": "9",
                      "seatNumber": 10,
                      "state": "ACTIVE"
                    },
                    {
                      "id": "Z2lkOi8vc2VhdC8xNDM5MQ==",
                      "type": "STANDARD",
                      "rowNumber": "9",
                      "seatNumber": 11,
                      "state": "ACTIVE"
                    },
                    {
                      "id": "Z2lkOi8vc2VhdC8xNDM5MA==",
                      "type": "STANDARD",
                      "rowNumber": "9",
                      "seatNumber": 12,
                      "state": "ACTIVE"
                    },
                    {
                      "id": "Z2lkOi8vc2VhdC8xNDM4OQ==",
                      "type": "STANDARD",
                      "rowNumber": "9",
                      "seatNumber": 13,
                      "state": "ACTIVE"
                    },
                    {
                      "id": "Z2lkOi8vc2VhdC8xNDM4OA==",
                      "type": "STANDARD",
                      "rowNumber": "9",
                      "seatNumber": 14,
                      "state": "ACTIVE"
                    }
                  ]
                },
                {
                  "rowNumber": "10",
                  "seats": [
                    {
                      "id": "Z2lkOi8vc2VhdC8xNDQxNQ==",
                      "type": "STANDARD",
                      "rowNumber": "10",
                      "seatNumber": 1,
                      "state": "ACTIVE"
                    },
                    {
                      "id": "Z2lkOi8vc2VhdC8xNDQxNA==",
                      "type": "STANDARD",
                      "rowNumber": "10",
                      "seatNumber": 2,
                      "state": "ACTIVE"
                    },
                    {
                      "id": "Z2lkOi8vc2VhdC8xNDQxMw==",
                      "type": "STANDARD",
                      "rowNumber": "10",
                      "seatNumber": 3,
                      "state": "ACTIVE"
                    },
                    {
                      "id": "Z2lkOi8vc2VhdC8xNDQxMg==",
                      "type": "STANDARD",
                      "rowNumber": "10",
                      "seatNumber": 4,
                      "state": "ACTIVE"
                    },
                    {
                      "id": "Z2lkOi8vc2VhdC8xNDQxMQ==",
                      "type": "STANDARD",
                      "rowNumber": "10",
                      "seatNumber": 5,
                      "state": "ACTIVE"
                    },
                    {
                      "id": "Z2lkOi8vc2VhdC8xNDQxMA==",
                      "type": "STANDARD",
                      "rowNumber": "10",
                      "seatNumber": 6,
                      "state": "ACTIVE"
                    },
                    {
                      "id": "Z2lkOi8vc2VhdC8xNDQwOQ==",
                      "type": "STANDARD",
                      "rowNumber": "10",
                      "seatNumber": 7,
                      "state": "SOLD"
                    },
                    {
                      "id": "Z2lkOi8vc2VhdC8xNDQwOA==",
                      "type": "STANDARD",
                      "rowNumber": "10",
                      "seatNumber": 8,
                      "state": "SOLD"
                    },
                    {
                      "id": "Z2lkOi8vc2VhdC8xNDQwNw==",
                      "type": "STANDARD",
                      "rowNumber": "10",
                      "seatNumber": 9,
                      "state": "SOLD"
                    },
                    {
                      "id": "Z2lkOi8vc2VhdC8xNDQwNg==",
                      "type": "STANDARD",
                      "rowNumber": "10",
                      "seatNumber": 10,
                      "state": "ACTIVE"
                    },
                    {
                      "id": "Z2lkOi8vc2VhdC8xNDQwNQ==",
                      "type": "STANDARD",
                      "rowNumber": "10",
                      "seatNumber": 11,
                      "state": "ACTIVE"
                    },
                    {
                      "id": "Z2lkOi8vc2VhdC8xNDQwNA==",
                      "type": "STANDARD",
                      "rowNumber": "10",
                      "seatNumber": 12,
                      "state": "ACTIVE"
                    },
                    {
                      "id": "Z2lkOi8vc2VhdC8xNDQwMw==",
                      "type": "STANDARD",
                      "rowNumber": "10",
                      "seatNumber": 13,
                      "state": "ACTIVE"
                    },
                    {
                      "id": "Z2lkOi8vc2VhdC8xNDQwMg==",
                      "type": "STANDARD",
                      "rowNumber": "10",
                      "seatNumber": 14,
                      "state": "ACTIVE"
                    }
                  ]
                },
                {
                  "rowNumber": "11",
                  "seats": [
                    {
                      "id": "Z2lkOi8vc2VhdC8xNDQyNw==",
                      "type": "VIP",
                      "rowNumber": "11",
                      "seatNumber": 1,
                      "state": "ACTIVE"
                    },
                    {
                      "id": "Z2lkOi8vc2VhdC8xNDQyNg==",
                      "type": "VIP",
                      "rowNumber": "11",
                      "seatNumber": 2,
                      "state": "ACTIVE"
                    },
                    {
                      "id": "Z2lkOi8vc2VhdC8xNDQyNQ==",
                      "type": "VIP",
                      "rowNumber": "11",
                      "seatNumber": 3,
                      "state": "ACTIVE"
                    },
                    {
                      "id": "Z2lkOi8vc2VhdC8xNDQyNA==",
                      "type": "VIP",
                      "rowNumber": "11",
                      "seatNumber": 4,
                      "state": "ACTIVE"
                    },
                    {
                      "id": "Z2lkOi8vc2VhdC8xNDQyMw==",
                      "type": "VIP",
                      "rowNumber": "11",
                      "seatNumber": 5,
                      "state": "ACTIVE"
                    },
                    {
                      "id": "Z2lkOi8vc2VhdC8xNDQyMg==",
                      "type": "VIP",
                      "rowNumber": "11",
                      "seatNumber": 6,
                      "state": "ACTIVE"
                    },
                    {
                      "id": "Z2lkOi8vc2VhdC8xNDQyMQ==",
                      "type": "VIP",
                      "rowNumber": "11",
                      "seatNumber": 7,
                      "state": "ACTIVE"
                    },
                    {
                      "id": "Z2lkOi8vc2VhdC8xNDQyMA==",
                      "type": "VIP",
                      "rowNumber": "11",
                      "seatNumber": 8,
                      "state": "ACTIVE"
                    },
                    {
                      "id": "Z2lkOi8vc2VhdC8xNDQxOQ==",
                      "type": "VIP",
                      "rowNumber": "11",
                      "seatNumber": 9,
                      "state": "ACTIVE"
                    },
                    {
                      "id": "Z2lkOi8vc2VhdC8xNDQxOA==",
                      "type": "VIP",
                      "rowNumber": "11",
                      "seatNumber": 10,
                      "state": "ACTIVE"
                    },
                    {
                      "id": "Z2lkOi8vc2VhdC8xNDQxNw==",
                      "type": "VIP",
                      "rowNumber": "11",
                      "seatNumber": 11,
                      "state": "ACTIVE"
                    },
                    {
                      "id": "Z2lkOi8vc2VhdC8xNDQxNg==",
                      "type": "VIP",
                      "rowNumber": "11",
                      "seatNumber": 12,
                      "state": "ACTIVE"
                    }
                  ]
                }
              ]
            },
            "priceBundle": {
              "minPrices": {
                "price": 160,
                "priceInBonuses": 4200
              },
              "items": [
                {
                  "price": 160,
                  "priceInBonuses": 4200,
                  "seatType": "STANDARD",
                  "canBePaidByBonuses": true
                },
                {
                  "price": 280,
                  "priceInBonuses": 5300,
                  "seatType": "VIP",
                  "canBePaidByBonuses": true
                }
              ]
            },
            "id": "Z2lkOi8vc2Vzc2lvbi8yNzQ4NTAy",
            "rentalTechnology": {
              "id": "Z2lkOi8vcmVudGFsdGVjaG5vbG9neS81",
              "name": "Cinetech+"
            },
            "cinemaHallId": "Z2lkOi8vY2luZW1haGFsbC8xMDY="
          }
        ]
      }
    }
  }
}